<?xml version="1.0" encoding="UTF-8"?>
<p:root xmlns:p="http://www.hitmakers.com/aof/customPlaces"
        xmlns:xsi="http://www.w3.org/2001/XMLSchema-instance"
        xsi:schemaLocation="http://www.hitmakers.com/aof/customPlaces ../../xsd/customPlaces.xsd">

    <!-- Горшок -->

    <p:place id="pi_1o_mt_hotm_pot" animType="EMPTY" imageId="44x66" name="Горшок" minPlayerStair="40" meetProbability="0">
        <p:blockingCreature probability="0"/>
        <p:states>

            <!-- стандартная реплика  -->
            <p:state id="default">
                <p:dialog>
                    <p:replica id="r1">
                        <p:mainText>Пустой горшок с узким горлышком... Вы не сдерживаете себя и утробно рычите в его нутро. В ответ горшок отдаёт сильным эхом вашего рыка. </p:mainText>
                        <p:answers>
                            <p:answer text="Мощно" goto="r1" out="true"/>
                        </p:answers>
                    </p:replica>
                </p:dialog>
            </p:state>


        </p:states>
    </p:place>

</p:root>