<?xml version="1.0" encoding="UTF-8"?>
<p:root xmlns:p="http://www.hitmakers.com/aof/customPlaces"
        xmlns:xsi="http://www.w3.org/2001/XMLSchema-instance"
        xsi:schemaLocation="http://www.hitmakers.com/aof/customPlaces ../../xsd/customPlaces.xsd">

    <!-- Ящик с патронами  -->

    <p:place id="pi_1o_it_ta_box_with_bullets" animType="EMPTY" imageId="76x91" name="Ящик с патронами" minPlayerStair="40"
             meetProbability="0">
        <p:blockingCreature probability="0"/>
        <p:states>

            <!-- стандартная реплика  -->
            <p:state id="default">
                <p:dialog>
                    <p:replica id="r1">
                        <p:mainText>В ящике полно патронов для мушкетов, ружий и пистолей. Увы, ничего там не спрятано... А пули вам ни к чему, их даже кентавр не купит... Он ими и пользоваться не умеет. </p:mainText>
                        <p:answers>
                            <p:answer text="Понимаю" goto="r1" out="true"/>
                        </p:answers>
                    </p:replica>
                </p:dialog>
            </p:state>

        </p:states>
    </p:place>

</p:root>